odoo/addons/so_report_hide_lines/README.rst
odoo/addons/so_report_hide_lines/__init__.py
odoo/addons/so_report_hide_lines/__manifest__.py
odoo/addons/so_report_hide_lines/i18n/es.po
odoo/addons/so_report_hide_lines/models/__init__.py
odoo/addons/so_report_hide_lines/models/sale_order_line.py
odoo/addons/so_report_hide_lines/report/sale_report_templates.xml
odoo/addons/so_report_hide_lines/static/description/icon.png
odoo/addons/so_report_hide_lines/views/sale_views.xml
odoo_addon_so_report_hide_lines-15.0.1.0.0.2.dist-info/METADATA
odoo_addon_so_report_hide_lines-15.0.1.0.0.2.dist-info/WHEEL
odoo_addon_so_report_hide_lines-15.0.1.0.0.2.dist-info/top_level.txt
odoo_addon_so_report_hide_lines-15.0.1.0.0.2.dist-info/RECORD
